celery_control/__init__.py
celery_control/conf.py
celery_control/metrics.py
celery_control/multiprocess.py
celery_control/observable.py
celery_control/receivers/__init__.py
celery_control/receivers/publish_signals_receiver.py
celery_control/receivers/task_signals_receiver.py
celery_control/receivers/worker_signals_receiver.py
celery_control/server/__init__.py
celery_control/server/exposition.py
celery_control/server/socket.py
celery_control/server/types.py
celery_control/server/wsgi.py
celery_control/server/wsgiref.py
celery_control/setup.py
celery_control/snapshot.py
celery_control/tracker.py
celery_control/utils/__init__.py
celery_control/utils/strtobool.py
celery_control-0.1.2.dist-info/LICENSE
celery_control-0.1.2.dist-info/METADATA
celery_control-0.1.2.dist-info/WHEEL
celery_control-0.1.2.dist-info/RECORD
