Metadata-Version: 2.1
Name: celery-control
Version: 0.1.2
Summary: 
Author: Anton Zubarev
Author-email: aszubarev@domclick.ru
Requires-Python: >=3.10,<4.0
Classifier: Programming Language :: Python :: 3
Classifier: Programming Language :: Python :: 3.10
Classifier: Programming Language :: Python :: 3.11
Classifier: Programming Language :: Python :: 3.12
Requires-Dist: celery (>=5.4,<6.0)
Requires-Dist: filelock (>=3.14.0,<4.0.0)
Requires-Dist: prometheus-client (>=0.20.0,<1.0.0)
